pydfu/__init__.py
pydfu/df.py
pydfu/fs.py
pydfu/scanner.py
pydfu-0.1.data/scripts/pydfu
pydfu-0.1.dist-info/DESCRIPTION.rst
pydfu-0.1.dist-info/METADATA
pydfu-0.1.dist-info/RECORD
pydfu-0.1.dist-info/WHEEL
pydfu-0.1.dist-info/metadata.json
pydfu-0.1.dist-info/top_level.txt
