Metadata-Version: 2.0
Name: pydfu
Version: 0.1
Summary: Disk and File system query
Home-page: https://github.com/rrajaravi/pydfu.git
Author: rrajaravi
Author-email: r.rajaravi@gmail.com
License: MIT
Platform: UNKNOWN
Classifier: Programming Language :: Python
Classifier: Programming Language :: Python :: 2
Classifier: License :: OSI Approved :: GNU General Public License (GPL)
Classifier: Operating System :: OS Independent
Classifier: Development Status :: 1 - Planning
Classifier: Environment :: Console
Classifier: Intended Audience :: Science/Research
